dispatches_sample_data/__init__.py
dispatches_sample_data/rts_gmlc/LICENSE.md
dispatches_sample_data/rts_gmlc/__init__.py
dispatches_sample_data/rts_gmlc/_fetch.py
dispatches_sample_data/rts_gmlc/SourceData/README.md
dispatches_sample_data/rts_gmlc/SourceData/branch.csv
dispatches_sample_data/rts_gmlc/SourceData/bus.csv
dispatches_sample_data/rts_gmlc/SourceData/dc_branch.csv
dispatches_sample_data/rts_gmlc/SourceData/gen.csv
dispatches_sample_data/rts_gmlc/SourceData/simulation_objects.csv
dispatches_sample_data/rts_gmlc/SourceData/storage.csv
dispatches_sample_data/rts_gmlc/SourceData/timeseries_pointers.csv
dispatches_sample_data/rts_gmlc/SourceData/HR_data/Final_Fits.csv
dispatches_sample_data/rts_gmlc/SourceData/HR_data/README.md
dispatches_sample_data/rts_gmlc/SourceData/HR_data/gen_oldHRs.csv
dispatches_sample_data/rts_gmlc/timeseries_data_files/README.md
dispatches_sample_data/rts_gmlc/timeseries_data_files/CSP/DAY_AHEAD_Natural_Inflow.csv
dispatches_sample_data/rts_gmlc/timeseries_data_files/CSP/REAL_TIME_Natural_Inflow.csv
dispatches_sample_data/rts_gmlc/timeseries_data_files/Hydro/DAY_AHEAD_hydro.csv
dispatches_sample_data/rts_gmlc/timeseries_data_files/Hydro/REAL_TIME_hydro.csv
dispatches_sample_data/rts_gmlc/timeseries_data_files/Load/DAY_AHEAD_regional_Load.csv
dispatches_sample_data/rts_gmlc/timeseries_data_files/Load/REAL_TIME_regional_Load.csv
dispatches_sample_data/rts_gmlc/timeseries_data_files/Load/origin/APS_Promod_2020.csv
dispatches_sample_data/rts_gmlc/timeseries_data_files/Load/origin/LDWP_Promod_2020.csv
dispatches_sample_data/rts_gmlc/timeseries_data_files/Load/origin/NEVP_Promod_2020.csv
dispatches_sample_data/rts_gmlc/timeseries_data_files/Load/origin/RT_APS_Promod_2020.csv
dispatches_sample_data/rts_gmlc/timeseries_data_files/Load/origin/RT_LDWP_Promod_2020.csv
dispatches_sample_data/rts_gmlc/timeseries_data_files/Load/origin/RT_NEVP_Promod_2020.csv
dispatches_sample_data/rts_gmlc/timeseries_data_files/PV/DAY_AHEAD_pv.csv
dispatches_sample_data-22.9.19.dist-info/METADATA
dispatches_sample_data-22.9.19.dist-info/WHEEL
dispatches_sample_data-22.9.19.dist-info/top_level.txt
dispatches_sample_data-22.9.19.dist-info/RECORD
