Metadata-Version: 2.1
Name: dispatches-sample-data
Version: 22.9.19
Summary: Sample datasets for the DISPATCHES project
Requires-Dist: importlib-metadata ; python_version < "3.8"
